finance_calculator_sk1/__init__.py
finance_calculator_sk1/__main__.py
finance_calculator_sk1/calculator.py
finance_calculator_sk1-0.1.dist-info/METADATA
finance_calculator_sk1-0.1.dist-info/WHEEL
finance_calculator_sk1-0.1.dist-info/entry_points.txt
finance_calculator_sk1-0.1.dist-info/top_level.txt
finance_calculator_sk1-0.1.dist-info/RECORD
