Metadata-Version: 2.1
Name: finance-calculator-sk1
Version: 0.1
Summary: A package for calculating net profit and ROI.
Author: Stanislav Kuleshov
Author-email: phtschmth171@gmail.com
